akl_cameras/__init__.py
akl_cameras/camera.py
akl_cameras/file.py
akl_cameras/photo.py
akl_cameras-0.1.0.dist-info/METADATA
akl_cameras-0.1.0.dist-info/WHEEL
akl_cameras-0.1.0.dist-info/RECORD
