Metadata-Version: 2.1
Name: akl-cameras
Version: 0.1.0
Summary: Tool that allow to operate cameras owned by AKL
Author: Jędrzej Stasik
Author-email: jedrzej.stasik@gmail.com
Requires-Python: >=3.9,<4.0
Classifier: Programming Language :: Python :: 3
Classifier: Programming Language :: Python :: 3.9
Classifier: Programming Language :: Python :: 3.10
Classifier: Programming Language :: Python :: 3.11
